{
    "list": [
        {
            "chapter_num": 0,
            "page_title_name": "般若波羅蜜多心經",
            "page_title_main": "抄寫心經能開啟智慧，破除妄念。"
        },
        {
            "chapter_num": 1,
            "page_title_name": "地藏菩薩本願經",
            "page_title_main": "記載地藏菩薩「地獄不空，誓不成佛」的大願，及其救度眾生的事蹟。抄寫此經能增長孝親之心，消除業障。"
        },
        {
            "chapter_num": 2,
            "page_title_name": "金剛般若波羅蜜經",
            "page_title_main": "闡述「應無所住而生其心」的無上法門。抄寫金剛經能斷除煩惱，成就無上菩提。"
        }
    ]
}